xdmod_mcp_data/__init__.py
xdmod_mcp_data/base_server.py
xdmod_mcp_data/server.py
xdmod_mcp_data-0.2.0.dist-info/METADATA
xdmod_mcp_data-0.2.0.dist-info/WHEEL
xdmod_mcp_data-0.2.0.dist-info/entry_points.txt
xdmod_mcp_data-0.2.0.dist-info/top_level.txt
xdmod_mcp_data-0.2.0.dist-info/RECORD
